{
  "setting": {},
  "condition": {
    "plugin": {
      "list": []
    },
    "game": {
      "list": []
    },
    "gamePlugin": {
      "list": []
    },
    "miniprogram": {
      "list": [
        {
          "name": "pages/posts/posts",
          "pathName": "pages/posts/posts",
          "query": "",
          "scene": null
        },
        {
          "name": "pages/post-detail/post-detail",
          "pathName": "pages/post-detail/post-detail",
          "query": "pid=2",
          "scene": null
        },
        {
          "name": "pages/movies/movies",
          "pathName": "pages/movies/movies",
          "query": "pid=2",
          "scene": null
        },
        {
          "name": "pages/movie-detail/movie-detail",
          "pathName": "pages/movie-detail/movie-detail",
          "query": "mid=312",
          "scene": null
        }
      ]
    }
  }
}